aku/__init__.py
aku/actions.py
aku/aku.py
aku/formatter.py
aku/parser.py
aku/tp.py
aku/utils.py
aku-0.2.6.dist-info/METADATA
aku-0.2.6.dist-info/WHEEL
aku-0.2.6.dist-info/top_level.txt
aku-0.2.6.dist-info/RECORD
