Metadata-Version: 2.1
Name: aku
Version: 0.2.6
Summary: An interactive annotation-driven ArgumentParser generator
Home-page: https://github.com/speedcell4/aku
Author: speedcell4
Author-email: speedcell4@gmail.com
License: MIT
Platform: UNKNOWN
Requires-Python: >=3.8
